MANIFEST.in
README.txt
setup.py
src/.DS_Store
src/medialog/.DS_Store
src/medialog/__init__.py
src/medialog.simpleslider.egg-info/PKG-INFO
src/medialog.simpleslider.egg-info/SOURCES.txt
src/medialog.simpleslider.egg-info/dependency_links.txt
src/medialog.simpleslider.egg-info/entry_points.txt
src/medialog.simpleslider.egg-info/namespace_packages.txt
src/medialog.simpleslider.egg-info/not-zip-safe
src/medialog.simpleslider.egg-info/requires.txt
src/medialog.simpleslider.egg-info/top_level.txt
src/medialog/simpleslider/.DS_Store
src/medialog/simpleslider/README.txt
src/medialog/simpleslider/__init__.py
src/medialog/simpleslider/config.py
src/medialog/simpleslider/configure.zcml
src/medialog/simpleslider/interfaces.py
src/medialog/simpleslider/settings.py
src/medialog/simpleslider/vocabulary.py
src/medialog/simpleslider/browser/.DS_Store
src/medialog/simpleslider/browser/__init__.py
src/medialog/simpleslider/browser/configure.zcml
src/medialog/simpleslider/browser/forms.py
src/medialog/simpleslider/browser/interfaces.py
src/medialog/simpleslider/browser/simpleslider.pt
src/medialog/simpleslider/browser/utils.py
src/medialog/simpleslider/browser/viewlets.py
src/medialog/simpleslider/browser/files/.DS_Store
src/medialog/simpleslider/browser/files/README.md
src/medialog/simpleslider/browser/files/responsiveslides.css
src/medialog/simpleslider/browser/files/responsiveslides.js
src/medialog/simpleslider/browser/files/responsiveslides.min.js
src/medialog/simpleslider/browser/files/themes/themes.css
src/medialog/simpleslider/browser/files/themes/themes.gif
src/medialog/simpleslider/browser/files/themes/themes.html
src/medialog/simpleslider/profiles/.DS_Store
src/medialog/simpleslider/profiles/default/actions.xml
src/medialog/simpleslider/profiles/default/browserlayer.xml
src/medialog/simpleslider/profiles/default/metadata.xml
src/medialog/simpleslider/profiles/default/viewlets.xml
src/medialog/simpleslider/tests/__init__.py
src/medialog/simpleslider/tests/base.py
src/medialog/simpleslider/tests/test_doctest.py
src/medialog/simpleslider/tests/test_example.py